fasm/__init__.py
fasm/model.py
fasm/output.py
fasm/tool.py
fasm/version.py
fasm/parser/__init__.py
fasm/parser/antlr.py
fasm/parser/antlr_to_tuple.cpython-39-darwin.so
fasm/parser/antlr_to_tuple.pyx
fasm/parser/fasm.tx
fasm/parser/libparse_fasm.dylib
fasm/parser/tags.py
fasm/parser/textx.py
fasm-0.0.2.post100.dist-info/LICENSE
fasm-0.0.2.post100.dist-info/METADATA
fasm-0.0.2.post100.dist-info/WHEEL
fasm-0.0.2.post100.dist-info/entry_points.txt
fasm-0.0.2.post100.dist-info/top_level.txt
fasm-0.0.2.post100.dist-info/RECORD
