Metadata-Version: 2.1
Name: fasm
Version: 0.0.2.post100
Summary: FPGA Assembly (FASM) Parser and Generation library
Home-page: https://github.com/chipsalliance/fasm
Author: F4PGA Authors
Author-email: f4pga-wg@lists.chipsalliance.org
License: UNKNOWN
Platform: UNKNOWN
Classifier: Programming Language :: Python :: 3
Classifier: License :: OSI Approved :: Apache Software License
Classifier: Operating System :: OS Independent
License-File: LICENSE
Requires-Dist: textx
